LICENSE
MANIFEST.in
README.rst
setup.py
arc3o/__init__.py
arc3o/core_functions.py
arc3o/mask_functions.py
arc3o/memls_functions_2D.py
arc3o/profile_functions.py
arc3o.egg-info/PKG-INFO
arc3o.egg-info/SOURCES.txt
arc3o.egg-info/dependency_links.txt
arc3o.egg-info/requires.txt
arc3o.egg-info/top_level.txt