Metadata-Version: 1.2
Name: arc3o
Version: 0.1
Summary: An observation operator for the Arctic Ocean for 6.9 GHz
Home-page: https://github.com/ClimateClara/arc3o
Author: Clara Burgard
Author-email: clara.burgard@gmail.com
License: GPL-3.0
Project-URL: Source, https://github.com/ClimateClara/arc3o
Project-URL: Tracker, https://github.com/ClimateClara/arc3o/issues
Keywords: earth-sciences climate-modeling sea-ice arctic oceanography remote-sensing
Platform: UNKNOWN
Classifier: Development Status :: 4 - Beta
Classifier: Intended Audience :: Science/Research
Classifier: License :: OSI Approved :: GNU General Public License v3 (GPLv3)
Classifier: Operating System :: OS Independent
Classifier: Programming Language :: Python :: 3 :: Only
Requires-Python: >=3.5
